numberninja/__init__.py
numberninja/cli.py
numberninja-0.0.1.dist-info/LICENSE
numberninja-0.0.1.dist-info/METADATA
numberninja-0.0.1.dist-info/WHEEL
numberninja-0.0.1.dist-info/entry_points.txt
numberninja-0.0.1.dist-info/top_level.txt
numberninja-0.0.1.dist-info/RECORD
