Metadata-Version: 2.1
Name: numberninja
Version: 0.0.1
Summary: A personal bookkeeping application
Author: René Moll
Project-URL: Homepage, https://github.com/renemoll/numberninja
Project-URL: Issues, https://github.com/renemoll/numberninja/issues
Classifier: Development Status :: 1 - Planning
Classifier: Programming Language :: Python :: 3
Classifier: License :: OSI Approved :: GNU General Public License v3 (GPLv3)
Classifier: Operating System :: OS Independent
Requires-Python: >=3.8
License-File: LICENSE
Provides-Extra: dev
Requires-Dist: black ; extra == 'dev'
Requires-Dist: ruff ; extra == 'dev'
